odoo/addons/l10n_ch_base_bank/README.rst
odoo/addons/l10n_ch_base_bank/__init__.py
odoo/addons/l10n_ch_base_bank/__manifest__.py
odoo/addons/l10n_ch_base_bank/i18n/de.po
odoo/addons/l10n_ch_base_bank/i18n/fr.po
odoo/addons/l10n_ch_base_bank/i18n/it.po
odoo/addons/l10n_ch_base_bank/i18n/l10n_ch_base_bank.pot
odoo/addons/l10n_ch_base_bank/migrations/11.0.1.1.0/post-migration.py
odoo/addons/l10n_ch_base_bank/models/__init__.py
odoo/addons/l10n_ch_base_bank/models/bank.py
odoo/addons/l10n_ch_base_bank/models/invoice.py
odoo/addons/l10n_ch_base_bank/static/description/icon.png
odoo/addons/l10n_ch_base_bank/tests/__init__.py
odoo/addons/l10n_ch_base_bank/tests/test_bank.py
odoo/addons/l10n_ch_base_bank/tests/test_bank_type.py
odoo/addons/l10n_ch_base_bank/tests/test_create_invoice.py
odoo/addons/l10n_ch_base_bank/tests/test_search_invoice.py
odoo/addons/l10n_ch_base_bank/views/bank.xml
odoo/addons/l10n_ch_base_bank/views/invoice.xml
odoo11_addon_l10n_ch_base_bank-11.0.1.1.1.dist-info/METADATA
odoo11_addon_l10n_ch_base_bank-11.0.1.1.1.dist-info/RECORD
odoo11_addon_l10n_ch_base_bank-11.0.1.1.1.dist-info/WHEEL
odoo11_addon_l10n_ch_base_bank-11.0.1.1.1.dist-info/top_level.txt
