Metadata-Version: 2.1
Name: odoo11-addon-l10n-ch-base-bank
Version: 11.0.1.1.1
Summary: Types and number validation for swiss electronic pmnt. DTA, ESR
Home-page: http://www.camptocamp.com
Author: Camptocamp,Odoo Community Association (OCA)
Author-email: support@odoo-community.org
License: AGPL-3
Platform: UNKNOWN
Classifier: Programming Language :: Python
Classifier: Framework :: Odoo
Classifier: License :: OSI Approved :: GNU Affero General Public License v3
Requires-Python: >=2.7, !=3.0.*, !=3.1.*, !=3.2.*, !=3.3.*, !=3.4.*
Requires-Dist: odoo11-addon-account-payment-partner
Requires-Dist: odoo (<11.1dev,>=11.0a)
